AlgebraicNumber/AlgebraicNumber.py
AlgebraicNumber/QMatrix.py
AlgebraicNumber/QPolynomial.py
AlgebraicNumber/__init__.py
AlgebraicNumber/inria_utils.py
AlgebraicNumber/utils.py
tests/TestBase.py
tests/__init__.py
tests/requirements.txt
tests/test_inria.py
tests/test_ops.py
AlgebraicNumber-2.4.4.dist-info/LICENSE
AlgebraicNumber-2.4.4.dist-info/METADATA
AlgebraicNumber-2.4.4.dist-info/WHEEL
AlgebraicNumber-2.4.4.dist-info/top_level.txt
AlgebraicNumber-2.4.4.dist-info/RECORD
