Metadata-Version: 2.1
Name: AlgebraicNumber
Version: 2.4.4
Summary: Manipulation of algebraic numbers
Home-page: https://gitlab.com/ydethe/algebraicnumber
Author: Yann de The
Author-email: ydethe@gmail.com
Project-URL: Documentation, https://ydethe.gitlab.io/algebraicnumber/docs
Project-URL: Source, https://gitlab.com/ydethe/algebraicnumber
Platform: any
Classifier: Development Status :: 3 - Alpha
Classifier: Intended Audience :: Developers
Classifier: License :: OSI Approved :: MIT License
Classifier: Operating System :: OS Independent
Classifier: Programming Language :: Python
Classifier: Programming Language :: Python :: 3.5
Classifier: Topic :: Software Development :: Libraries :: Python Modules
Requires-Python: >=3.5
License-File: LICENSE
Requires-Dist: numpy (>=1.11.1)
Requires-Dist: scipy (>=0.18.1)
Requires-Dist: rich
